timeline/__init__.py
timeline/configurations.py
timeline/move_elements.py
timeline/utils/paragraph.py
timeline/utils/placeholder.py
timeline/utils/shapes.py
timeline_craft-0.1.5.dist-info/METADATA
timeline_craft-0.1.5.dist-info/WHEEL
timeline_craft-0.1.5.dist-info/top_level.txt
timeline_craft-0.1.5.dist-info/RECORD
