Metadata-Version: 2.4
Name: timeline-craft
Version: 0.1.5
Summary: A Python library for creating timeline visualizations in PowerPoint
Author-email: Don Yin <don_yin@outlook.com>
Project-URL: Homepage, https://github.com/Don-Yin/timeline-craft
Requires-Python: >=3.12
Requires-Dist: python-pptx
Requires-Dist: webcolors
